{"status":"done","publicPath":"/static/bundle_webapp/","chunks":{"app":[{"name":"app.9585412616bf96ac02bd.css","publicPath":"/static/bundle_webapp/app.9585412616bf96ac02bd.css","path":"/Users/viktor/Code/holis/core/webapp/assets/bundle_webapp/app.9585412616bf96ac02bd.css"},{"name":"app.9585412616bf96ac02bd.js","publicPath":"/static/bundle_webapp/app.9585412616bf96ac02bd.js","path":"/Users/viktor/Code/holis/core/webapp/assets/bundle_webapp/app.9585412616bf96ac02bd.js"},{"name":"app.9585412616bf96ac02bd.css.map","publicPath":"/static/bundle_webapp/app.9585412616bf96ac02bd.css.map","path":"/Users/viktor/Code/holis/core/webapp/assets/bundle_webapp/app.9585412616bf96ac02bd.css.map"},{"name":"app.9585412616bf96ac02bd.js.map","publicPath":"/static/bundle_webapp/app.9585412616bf96ac02bd.js.map","path":"/Users/viktor/Code/holis/core/webapp/assets/bundle_webapp/app.9585412616bf96ac02bd.js.map"}]}}