{"status":"done","publicPath":"/static/bundle_webapp/","chunks":{"app":[{"name":"app.7e8ec7d8847f1c58b558.css","publicPath":"/static/bundle_webapp/app.7e8ec7d8847f1c58b558.css","path":"/home/viktor/code/holis/core/webapp/assets/bundle_webapp/app.7e8ec7d8847f1c58b558.css"},{"name":"app.7e8ec7d8847f1c58b558.js","publicPath":"/static/bundle_webapp/app.7e8ec7d8847f1c58b558.js","path":"/home/viktor/code/holis/core/webapp/assets/bundle_webapp/app.7e8ec7d8847f1c58b558.js"},{"name":"app.7e8ec7d8847f1c58b558.css.map","publicPath":"/static/bundle_webapp/app.7e8ec7d8847f1c58b558.css.map","path":"/home/viktor/code/holis/core/webapp/assets/bundle_webapp/app.7e8ec7d8847f1c58b558.css.map"},{"name":"app.7e8ec7d8847f1c58b558.js.map","publicPath":"/static/bundle_webapp/app.7e8ec7d8847f1c58b558.js.map","path":"/home/viktor/code/holis/core/webapp/assets/bundle_webapp/app.7e8ec7d8847f1c58b558.js.map"}]}}